gym_square/__init__.py
gym_square/envs/__init__.py
gym_square/envs/square_env.py
gym_square/envs/square_world/keyboard.py
gym_square/envs/square_world/reward.py
gym_square/envs/square_world/square_world.py
gym_square/envs/square_world/agent.py
gym_square/envs/square_world/__init__.py
gym_square/envs/square_world/grid.py
gym_square/test/test_squareworldenv.py
gym_square/test/__init__.py
gym_square/test/test_human_input.py
gym_square-0.0.1.dist-info/top_level.txt
gym_square-0.0.1.dist-info/metadata.json
gym_square-0.0.1.dist-info/DESCRIPTION.rst
gym_square-0.0.1.dist-info/RECORD
gym_square-0.0.1.dist-info/WHEEL
gym_square-0.0.1.dist-info/METADATA
