Metadata-Version: 2.0
Name: gym-square
Version: 0.0.1
Summary: A simple square world environment for openai/gym
Home-page: https://github.com/gpldecha/gym-square
Author: Guillaume de Chambrier
Author-email: chambrierg@gmail.com
License: MIT
Platform: UNKNOWN
Requires-Dist: gym
